[
  {"French": "bonjour", "English": "hello"},
  {"French": "merci", "English": "thank you"},
  {"French": "s'il vous plaît", "English": "please"},
  {"French": "oui", "English": "yes"},
  {"French": "non", "English": "no"},
  {"French": "excusez-moi", "English": "excuse me"},
  {"French": "pardon", "English": "sorry"},
  {"French": "je suis", "English": "I am"},
  {"French": "tu es", "English": "you are"},
  {"French": "il est", "English": "he is"},
  {"French": "elle est", "English": "she is"},
  {"French": "nous sommes", "English": "we are"},
  {"French": "ils sont", "English": "they are"},
  {"French": "elles sont", "English": "they (females) are"},
  {"French": "j'ai", "English": "I have"},
  {"French": "tu as", "English": "you have"},
  {"French": "il a", "English": "he has"},
  {"French": "elle a", "English": "she has"},
  {"French": "nous avons", "English": "we have"},
  {"French": "ils ont", "English": "they have"},
  {"French": "elles ont", "English": "they (females) have"},
  {"French": "je vais", "English": "I go"},
  {"French": "tu vas", "English": "you go"},
  {"French": "il va", "English": "he goes"},
  {"French": "elle va", "English": "she goes"},
  {"French": "nous allons", "English": "we go"},
  {"French": "ils vont", "English": "they go"},
  {"French": "elles vont", "English": "they (females) go"},
  {"French": "je veux", "English": "I want"},
  {"French": "tu veux", "English": "you want"},
  {"French": "il veut", "English": "he wants"},
  {"French": "elle veut", "English": "she wants"},
  {"French": "nous voulons", "English": "we want"},
  {"French": "ils veulent", "English": "they want"},
  {"French": "elles veulent", "English": "they (females) want"},
  {"French": "je peux", "English": "I can"},
  {"French": "tu peux", "English": "you can"},
  {"French": "il peut", "English": "he can"},
  {"French": "elle peut", "English": "she can"},
  {"French": "nous pouvons", "English": "we can"},
  {"French": "ils peuvent", "English": "they can"},
  {"French": "elles peuvent", "English": "they (females) can"},
  {"French": "l'eau", "English": "water"},
  {"French": "le pain", "English": "bread"},
  {"French": "le fromage", "English": "cheese"},
  {"French": "la pomme", "English": "apple"},
  {"French": "la banane", "English": "banana"},
  {"French": "le vin", "English": "wine"},
  {"French": "le café", "English": "coffee"},
  {"French": "le thé", "English": "tea"},
  {"French": "le lait", "English": "milk"},
  {"French": "le sucre", "English": "sugar"},
  {"French": "le sel", "English": "salt"},
  {"French": "la voiture", "English": "car"},
  {"French": "la maison", "English": "house"},
  {"French": "le livre", "English": "book"},
  {"French": "le téléphone", "English": "phone"},
  {"French": "l'ordinateur", "English": "computer"},
  {"French": "l'école", "English": "school"},
  {"French": "le travail", "English": "work"},
  {"French": "l'hôpital", "English": "hospital"},
  {"French": "le restaurant", "English": "restaurant"},
  {"French": "la chambre", "English": "room"},
  {"French": "la salle de bain", "English": "bathroom"},
  {"French": "le lit", "English": "bed"},
  {"French": "la table", "English": "table"},
  {"French": "la chaise", "English": "chair"},
  {"French": "la fenêtre", "English": "window"},
  {"French": "la porte", "English": "door"},
  {"French": "le chien", "English": "dog"},
  {"French": "le chat", "English": "cat"},
  {"French": "l'oiseau", "English": "bird"},
  {"French": "le cheval", "English": "horse"},
  {"French": "la vache", "English": "cow"},
  {"French": "le cochon", "English": "pig"},
  {"French": "la poule", "English": "hen"},
  {"French": "le poisson", "English": "fish"},
  {"French": "la mer", "English": "sea"},
  {"French": "la montagne", "English": "mountain"},
  {"French": "la ville", "English": "city"},
  {"French": "le village", "English": "village"},
  {"French": "la route", "English": "road"},
  {"French": "le chemin", "English": "path"},
  {"French": "le pont", "English": "bridge"},
  {"French": "le parc", "English": "park"},
  {"French": "le jardin", "English": "garden"},
  {"French": "l'arbre", "English": "tree"},
  {"French": "la fleur", "English": "flower"},
  {"French": "le soleil", "English": "sun"},
  {"French": "la lune", "English": "moon"},
  {"French": "l'étoile", "English": "star"},
  {"French": "le ciel", "English": "sky"},
  {"French": "le vent", "English": "wind"},
  {"French": "le feu", "English": "fire"}
]
